admobilize_malos-0.0.2-py3.6-nspkg.pth
admobilize/malos/__init__.py
admobilize/malos/cli.py
admobilize/malos/driver.py
admobilize_malos-0.0.2.dist-info/LICENSE
admobilize_malos-0.0.2.dist-info/METADATA
admobilize_malos-0.0.2.dist-info/WHEEL
admobilize_malos-0.0.2.dist-info/entry_points.txt
admobilize_malos-0.0.2.dist-info/namespace_packages.txt
admobilize_malos-0.0.2.dist-info/top_level.txt
admobilize_malos-0.0.2.dist-info/RECORD
