Metadata-Version: 2.1
Name: admobilize-malos
Version: 0.0.2
Summary: AdMobilize Malos Library
Home-page: https://bitbucket.com/admobilize/malos-python
Author: AdMobilize Team
Author-email: devel@admobilize.com
License: GPLv3
Platform: Posix; MacOS X; Windows
Classifier: Development Status :: 3 - Alpha
Classifier: Intended Audience :: Developers
Classifier: Programming Language :: Python
Classifier: Programming Language :: Python :: 3.6
Classifier: Programming Language :: Python :: 3.7
Requires-Python: >=3.6.*
Requires-Dist: docopt (>=0.6.2)
Requires-Dist: admobilizeapis (>=2020.06.18r1)
Requires-Dist: pyzmq (>=18.0.1)
